bser_client/__init__.py
bser_python_client-0.0.4.dist-info/LICENSE
bser_python_client-0.0.4.dist-info/METADATA
bser_python_client-0.0.4.dist-info/WHEEL
bser_python_client-0.0.4.dist-info/top_level.txt
bser_python_client-0.0.4.dist-info/RECORD
