Metadata-Version: 2.1
Name: bser-python-client
Version: 0.0.4
Summary: A Python API client for bser-open-api
Home-page: https://github.com/myungseokang/bser-python-client
Author: myungseokang
Author-email: iam@myungseokang.dev
License: UNKNOWN
Platform: UNKNOWN
Classifier: Programming Language :: Python :: 3
Classifier: License :: OSI Approved :: MIT License
Classifier: Operating System :: OS Independent
Requires-Python: >=3.6
